candl/.DS_Store
candl/__init__.py
candl/constants.py
candl/interface.py
candl/io.py
candl/lib.py
candl/likelihood.py
candl/plots.py
candl/tools.py
candl/tests/.DS_Store
candl/tests/__init__.py
candl/transformations/.DS_Store
candl/transformations/__init__.py
candl/transformations/abstract_base.py
candl/transformations/common.py
candl/transformations/common_lensing.py
candl/transformations/low_ell_BB.py
candl_like-2.2.0.dist-info/licenses/LICENCE.txt
candl_like-2.2.0.dist-info/WHEEL
candl_like-2.2.0.dist-info/METADATA
candl_like-2.2.0.dist-info/RECORD
