Metadata-Version: 2.4
Name: candl-like
Version: 2.2.0
Summary: Differentiable Likelihood for CMB Analysis
Author-email: "L. Balkenhol" <lennart.balkenhol@iap.fr>, "C. Trendafilova" <ctrendaf@illinois.edu>, "K. Benabed" <benabed@iap.fr>, "S. Galli" <gallis@iap.fr>
Requires-Python: >=3.9
Classifier: Programming Language :: Python :: 3
Classifier: Operating System :: OS Independent
License-File: LICENCE.txt
Requires-Dist: pyyaml >= 6.0
Requires-Dist: numpy >= 1.23.5
Requires-Dist: scipy >= 1.10.1
Requires-Dist: matplotlib >= 3.7.1
Requires-Dist: clipy-like >= 0.11
Requires-Dist: sphinx==6.2.1 ; extra == "docs"
Requires-Dist: sphinx-collapse==0.1.2 ; extra == "docs"
Requires-Dist: sphinx-book-theme==1.0.1 ; extra == "docs"
Requires-Dist: numpydoc==1.6.0 ; extra == "docs"
Requires-Dist: myst-parser==2.0.0 ; extra == "docs"
Requires-Dist: numpy ; extra == "docs"
Project-URL: Source, https://github.com/Lbalkenhol/candl
Provides-Extra: docs
